yooncloud_core/__init__.py
yooncloud_core/data/__init__.py
yooncloud_core/data/athena.py
yooncloud_core/data/base.py
yooncloud_core/data/koreadaychart.py
yooncloud_core/data/koreatickchart.py
yooncloud_core/data/s3.py
yooncloud_core/state/State.py
yooncloud_core/state/__init__.py
yooncloud_core/strategy/__init__.py
yooncloud_core/strategy/data.py
yooncloud_core/strategy/indicator.py
yooncloud_core/strategy/signal.py
yooncloud_core/strategy/strategy.py
yooncloud_core-0.0.18.dist-info/METADATA
yooncloud_core-0.0.18.dist-info/WHEEL
yooncloud_core-0.0.18.dist-info/top_level.txt
yooncloud_core-0.0.18.dist-info/RECORD
